api/__init__.py
api/client.py
cli/__init__.py
cli/deepseek_cli.py
config/__init__.py
config/settings.py
deepseek_cli-0.2.4.dist-info/licenses/LICENSE
handlers/__init__.py
handlers/chat_handler.py
handlers/command_handler.py
handlers/error_handler.py
utils/__init__.py
utils/exceptions.py
utils/version_checker.py
deepseek_cli-0.2.4.dist-info/METADATA
deepseek_cli-0.2.4.dist-info/WHEEL
deepseek_cli-0.2.4.dist-info/entry_points.txt
deepseek_cli-0.2.4.dist-info/top_level.txt
deepseek_cli-0.2.4.dist-info/RECORD
