Metadata-Version: 2.4
Name: deepseek-cli
Version: 0.2.4
Summary: A powerful CLI for interacting with DeepSeek's AI models
Home-page: https://github.com/PierrunoYT/deepseek-cli
Author: PierrunoYT
Author-email: PierrunoYT <pierrebruno@hotmail.ch>
License-Expression: MIT
Project-URL: Homepage, https://github.com/PierrunoYT/deepseek-cli
Classifier: Development Status :: 4 - Beta
Classifier: Intended Audience :: Developers
Classifier: Operating System :: OS Independent
Classifier: Programming Language :: Python :: 3
Classifier: Programming Language :: Python :: 3.7
Classifier: Programming Language :: Python :: 3.8
Classifier: Programming Language :: Python :: 3.9
Classifier: Programming Language :: Python :: 3.10
Classifier: Programming Language :: Python :: 3.11
Classifier: Topic :: Software Development :: Libraries :: Python Modules
Classifier: Topic :: Scientific/Engineering :: Artificial Intelligence
Requires-Python: >=3.7
License-File: LICENSE
Requires-Dist: openai>=1.0.0
Requires-Dist: requests>=2.31.0
Requires-Dist: typing-extensions>=4.7.0
Requires-Dist: pydantic>=2.0.0
Requires-Dist: setuptools>=42.0.0
Requires-Dist: rich>=14.0.0
Requires-Dist: pyfiglet>=1.0.3
Dynamic: author
Dynamic: home-page
Dynamic: license-file
Dynamic: requires-python
